vm_manager/__init__.py
vm_manager/logger.py
vm_manager/manager.py
vm_manager/util.py
vm_manager/vm.py
vm_manager-0.1.1.dist-info/METADATA
vm_manager-0.1.1.dist-info/WHEEL
vm_manager-0.1.1.dist-info/entry_points.txt
vm_manager-0.1.1.dist-info/licenses/LICENSE
vm_manager-0.1.1.dist-info/RECORD
