Metadata-Version: 2.1
Name: vm-manager
Version: 0.1.1
Summary: vm-manager is a CLI tool for managing one or more VMware virtual machines using various commands
Project-URL: homepage, https://github.com/han-keong/vm-manager
Project-URL: documentation, https://readthedocs.org
Project-URL: repository, https://github.com/han-keong/vm-manager.git
Project-URL: changelog, https://github.com/han-keong/vm-manager/blob/master/CHANGELOG.md
Author-email: Xie Han Keong <hk997@live.com>
License: MIT License
License-File: LICENSE
Keywords: automation,cli,desktop,home,manager,vm,vmware
Classifier: Development Status :: 4 - Beta
Classifier: Environment :: Console
Classifier: Intended Audience :: End Users/Desktop
Classifier: Operating System :: Microsoft :: Windows :: Windows 10
Classifier: Programming Language :: Python
Classifier: Topic :: Home Automation
Requires-Python: >=3.10
Requires-Dist: vix
